musicbot/__init__.py
musicbot/config.py
musicbot/defaults.py
musicbot/file.py
musicbot/folder.py
musicbot/helpers.py
musicbot/local.py
musicbot/main.py
musicbot/music.py
musicbot/music_filter.py
musicbot/musicdb.py
musicbot/object.py
musicbot/one_way_bool.py
musicbot/playlist.py
musicbot/playlist_options.py
musicbot/scan_folders.py
musicbot/spotify.py
musicbot/version.py
musicbot/cli/__init__.py
musicbot/cli/config.py
musicbot/cli/file.py
musicbot/cli/music_filter.py
musicbot/cli/musicdb.py
musicbot/cli/options.py
musicbot/cli/playlist.py
musicbot/cli/scan_folders.py
musicbot/cli/spotify.py
musicbot/commands/__init__.py
musicbot/commands/database.py
musicbot/commands/folder.py
musicbot/commands/local.py
musicbot/commands/music.py
musicbot/commands/spotify.py
musicbot/commands/youtube.py
musicbot/queries/delete_musics.edgeql
musicbot/queries/delete_musics_async_edgeql.py
musicbot/queries/drop_schema.edgeql
musicbot/queries/drop_schema_async_edgeql.py
musicbot/queries/gen_bests.edgeql
musicbot/queries/gen_bests_async_edgeql.py
musicbot/queries/gen_playlist.edgeql
musicbot/queries/gen_playlist_async_edgeql.py
musicbot/queries/pike_keywords.edgeql
musicbot/queries/pike_keywords_async_edgeql.py
musicbot/queries/remove.edgeql
musicbot/queries/remove_async_edgeql.py
musicbot/queries/select_artists.edgeql
musicbot/queries/select_artists_async_edgeql.py
musicbot/queries/select_folder.edgeql
musicbot/queries/select_folder_async_edgeql.py
musicbot/queries/soft_clean.edgeql
musicbot/queries/soft_clean_async_edgeql.py
musicbot/queries/upsert_album.edgeql
musicbot/queries/upsert_album_async_edgeql.py
musicbot/queries/upsert_artist.edgeql
musicbot/queries/upsert_artist_async_edgeql.py
musicbot/queries/upsert_async_edgeql.py
musicbot/queries/upsert_folder.edgeql
musicbot/queries/upsert_folder_async_edgeql.py
musicbot/queries/upsert_genre.edgeql
musicbot/queries/upsert_genre_async_edgeql.py
musicbot/queries/upsert_keyword.edgeql
musicbot/queries/upsert_keyword_async_edgeql.py
musicbot-0.10.0.dist-info/METADATA
musicbot-0.10.0.dist-info/WHEEL
musicbot-0.10.0.dist-info/entry_points.txt
musicbot-0.10.0.dist-info/RECORD
