Metadata-Version: 2.3
Name: musicbot
Version: 0.10.0
Summary: Music swiss army knife
License-Expression: MIT
Requires-Python: >=3.11
Requires-Dist: async-lru>=2.0.4
Requires-Dist: beartype>=0.19.0
Requires-Dist: click-skeleton>=0.30.1
Requires-Dist: click>=8.1.7
Requires-Dist: colorlog>=6.8.2
Requires-Dist: edgedb>=2.1.0
Requires-Dist: fuzzywuzzy>=0.18.0
Requires-Dist: httpx>=0.27.2
Requires-Dist: humanize>=4.11.0
Requires-Dist: ipython>=8.28.0
Requires-Dist: more-itertools>=10.5.0
Requires-Dist: mutagen>=1.47.0
Requires-Dist: natsort>=8.4.0
Requires-Dist: orjson>=3.10.7
Requires-Dist: pgcli>=4.1.0
Requires-Dist: progressbar3>=4.3.4
Requires-Dist: psycopg>=3.2.3
Requires-Dist: pyacoustid>=1.3.0
Requires-Dist: pydantic-core>=2.24.2
Requires-Dist: pydub>=0.25.1
Requires-Dist: pygments>=2.18.0
Requires-Dist: python-levenshtein>=0.26.0
Requires-Dist: python-slugify>=8.0.4
Requires-Dist: requests>=2.32.3
Requires-Dist: rich>=13.9.2
Requires-Dist: ruamel-yaml>=0.18.6
Requires-Dist: shazamio>=0.6.0
Requires-Dist: spotipy>=2.24.0
Requires-Dist: textual>=0.83.0
Requires-Dist: watchfiles>=0.24.0
Requires-Dist: yaspin>=3.1.0
Requires-Dist: yt-dlp>=2024.10.7
